cccc.py
cccc_pair-0.3.30.data/data/.cccc/cccc_tui.py
cccc_pair-0.3.30.data/data/.cccc/delivery.py
cccc_pair-0.3.30.data/data/.cccc/evidence_runner.py
cccc_pair-0.3.30.data/data/.cccc/mailbox.py
cccc_pair-0.3.30.data/data/.cccc/orchestrator_tmux.py
cccc_pair-0.3.30.data/data/.cccc/panel_status.py
cccc_pair-0.3.30.data/data/.cccc/prompt_weaver.py
cccc_pair-0.3.30.data/data/.cccc/tui_diagnostics.py
cccc_pair-0.3.30.data/data/.cccc/adapters/bridge_discord.py
cccc_pair-0.3.30.data/data/.cccc/adapters/bridge_slack.py
cccc_pair-0.3.30.data/data/.cccc/adapters/bridge_telegram.py
cccc_pair-0.3.30.data/data/.cccc/adapters/bridge_wecom.py
cccc_pair-0.3.30.data/data/.cccc/adapters/outbox_consumer.py
cccc_pair-0.3.30.data/data/.cccc/common/__init__.py
cccc_pair-0.3.30.data/data/.cccc/common/config.py
cccc_pair-0.3.30.data/data/.cccc/common/status_format.py
cccc_pair-0.3.30.data/data/.cccc/orchestrator/auto_compact.py
cccc_pair-0.3.30.data/data/.cccc/orchestrator/bridge_runtime.py
cccc_pair-0.3.30.data/data/.cccc/orchestrator/command_queue.py
cccc_pair-0.3.30.data/data/.cccc/orchestrator/command_queue_runtime.py
cccc_pair-0.3.30.data/data/.cccc/orchestrator/events.py
cccc_pair-0.3.30.data/data/.cccc/orchestrator/foreman.py
cccc_pair-0.3.30.data/data/.cccc/orchestrator/foreman_scheduler.py
cccc_pair-0.3.30.data/data/.cccc/orchestrator/handoff.py
cccc_pair-0.3.30.data/data/.cccc/orchestrator/handoff_helpers.py
cccc_pair-0.3.30.data/data/.cccc/orchestrator/json_util.py
cccc_pair-0.3.30.data/data/.cccc/orchestrator/keepalive.py
cccc_pair-0.3.30.data/data/.cccc/orchestrator/launcher.py
cccc_pair-0.3.30.data/data/.cccc/orchestrator/logging_util.py
cccc_pair-0.3.30.data/data/.cccc/orchestrator/mailbox_pipeline.py
cccc_pair-0.3.30.data/data/.cccc/orchestrator/nudge.py
cccc_pair-0.3.30.data/data/.cccc/orchestrator/policy_filter.py
cccc_pair-0.3.30.data/data/.cccc/orchestrator/status.py
cccc_pair-0.3.30.data/data/.cccc/orchestrator/task_manager.py
cccc_pair-0.3.30.dist-info/licenses/LICENSE
cccc_pair-0.3.30.dist-info/METADATA
cccc_pair-0.3.30.dist-info/WHEEL
cccc_pair-0.3.30.dist-info/entry_points.txt
cccc_pair-0.3.30.dist-info/top_level.txt
cccc_pair-0.3.30.dist-info/RECORD
