Metadata-Version: 2.4
Name: cccc-pair
Version: 0.3.30
Summary: Autonomous dual-AI orchestration runtime delivering evidence-first, small-step software execution with tmux-managed peers, governed handoffs, and IM bridge integration
Author-email: ChesterRa <ra@ike.ba>
License: Apache-2.0
Project-URL: Homepage, https://github.com/ChesterRa/cccc
Project-URL: Repository, https://github.com/ChesterRa/cccc
Project-URL: Issues, https://github.com/ChesterRa/cccc/issues
Keywords: orchestrator,tmux,ai,rfd,pair,collaboration
Classifier: Development Status :: 5 - Production/Stable
Classifier: Intended Audience :: Developers
Classifier: License :: OSI Approved :: MIT License
Classifier: Programming Language :: Python
Classifier: Programming Language :: Python :: 3
Classifier: Programming Language :: Python :: 3 :: Only
Classifier: Programming Language :: Python :: 3.9
Classifier: Programming Language :: Python :: 3.10
Classifier: Programming Language :: Python :: 3.11
Classifier: Environment :: Console
Classifier: Operating System :: POSIX :: Linux
Classifier: Operating System :: MacOS
Classifier: Topic :: Software Development :: Build Tools
Requires-Python: >=3.9
License-File: LICENSE
Requires-Dist: PyYAML>=6.0
Requires-Dist: prompt_toolkit>=3.0.52
Requires-Dist: pydantic>=2.0
Dynamic: license-file
